{"cameraMode":{"drawMode":0,"name":"Shaded","section":"Shading Mode"},"sceneLighting":false,"audioPlay":false,"sceneViewState":{"showFog":true,"showMaterialUpdate":false,"showSkybox":false,"showFlares":true,"showImageEffects":true,"showParticleSystems":true},"in2DMode":false,"pivot":{"x":-6.5553083419799809,"y":13.691085815429688,"z":33.78843688964844},"rotation":{"x":0.008377846330404282,"y":-0.9895271062850952,"z":0.13017603754997254,"w":0.06275054812431336},"size":3.7532718181610109,"orthographic":false}